LICENSE.txt
MANIFEST.in
README.md
setup.py
eldar_extended/__init__.py
eldar_extended/entry.py
eldar_extended/gui.py
eldar_extended/index.py
eldar_extended/indexops.py
eldar_extended/match.py
eldar_extended/operators.py
eldar_extended/query.py
eldar_extended/regex.py
eldar_extended/trie.py
eldar_extended.egg-info/PKG-INFO
eldar_extended.egg-info/SOURCES.txt
eldar_extended.egg-info/dependency_links.txt
eldar_extended.egg-info/top_level.txt