Metadata-Version: 2.1
Name: eldar-extended
Version: 0.1.0
Summary: Boolean text search in Python
Home-page: https://github.com/ClementChauvet/eldar_extended
Author: Maixent Chenebaux, Clement Chauvet
Author-email: max.chbx@gmail.com, clement.chauvet@univ-lille.fr
Classifier: Programming Language :: Python :: 3.9
Classifier: Operating System :: OS Independent
License-File: LICENSE.txt
